hide_frames.py
hide_frames-1.0.1.dist-info/LICENSE
hide_frames-1.0.1.dist-info/METADATA
hide_frames-1.0.1.dist-info/WHEEL
hide_frames-1.0.1.dist-info/top_level.txt
hide_frames-1.0.1.dist-info/RECORD
