Metadata-Version: 2.1
Name: hide-frames
Version: 1.0.1
Summary: Hide your ugly wrapper frames: func(*args, **kwargs)
License: GNU GENERAL PUBLIC LICENSE
Project-URL: Homepage, https://github.com/tovicheung/hide_frames
Classifier: License :: OSI Approved :: MIT License
Classifier: Programming Language :: Python
Classifier: Programming Language :: Python :: 3
License-File: LICENSE
